botafar/__init__.py
botafar/__main__.py
botafar/_internal/callback_executor.py
botafar/_internal/constants.py
botafar/_internal/exceptions.py
botafar/_internal/function_utils.py
botafar/_internal/log_formatter.py
botafar/_internal/string_utils.py
botafar/_internal/callbacks/__init__.py
botafar/_internal/callbacks/callback_base.py
botafar/_internal/controls/__init__.py
botafar/_internal/controls/button.py
botafar/_internal/controls/control_base.py
botafar/_internal/controls/joystick.py
botafar/_internal/controls/slider.py
botafar/_internal/data_channel/__init__.py
botafar/_internal/data_channel/data_channel.py
botafar/_internal/data_channel/json_utils.py
botafar/_internal/decorators/__init__.py
botafar/_internal/decorators/decorator_base.py
botafar/_internal/decorators/decorators.py
botafar/_internal/events/__init__.py
botafar/_internal/events/event.py
botafar/_internal/events/system_event.py
botafar/_internal/main/__init__.py
botafar/_internal/main/botafar_base.py
botafar/_internal/main/cli.py
botafar/_internal/main/main.py
botafar/_internal/states/__init__.py
botafar/_internal/states/keyboard_client_state.py
botafar/_internal/states/server_event_prosessor.py
botafar/_internal/states/server_state_machine.py
botafar-0.0.10.dist-info/entry_points.txt
botafar-0.0.10.dist-info/LICENSE
botafar-0.0.10.dist-info/WHEEL
botafar-0.0.10.dist-info/METADATA
botafar-0.0.10.dist-info/RECORD
